ghrepo/__init__.py
ghrepo/__main__.py
ghrepo/py.typed
ghrepo-0.7.1.dist-info/METADATA
ghrepo-0.7.1.dist-info/WHEEL
ghrepo-0.7.1.dist-info/entry_points.txt
ghrepo-0.7.1.dist-info/licenses/LICENSE
ghrepo-0.7.1.dist-info/RECORD
