Metadata-Version: 2.3
Name: ghrepo
Version: 0.7.1
Summary: Parse & construct GitHub repository URLs & specifiers
Project-URL: Source Code, https://github.com/jwodder/ghrepo
Project-URL: Bug Tracker, https://github.com/jwodder/ghrepo/issues
Author-email: John Thorvald Wodder II <ghrepo@varonathe.org>
License: MIT
Keywords: GitHub,URL parsing,repository
Classifier: Intended Audience :: Developers
Classifier: Intended Audience :: Information Technology
Classifier: License :: OSI Approved :: MIT License
Classifier: Programming Language :: Python :: 3
Classifier: Programming Language :: Python :: 3 :: Only
Classifier: Programming Language :: Python :: 3.8
Classifier: Programming Language :: Python :: 3.9
Classifier: Programming Language :: Python :: 3.10
Classifier: Programming Language :: Python :: 3.11
Classifier: Programming Language :: Python :: 3.12
Classifier: Programming Language :: Python :: 3.13
Classifier: Programming Language :: Python :: Implementation :: CPython
Classifier: Programming Language :: Python :: Implementation :: PyPy
Classifier: Topic :: Software Development :: Version Control
Classifier: Topic :: Software Development :: Version Control :: Git
Classifier: Typing :: Typed
Requires-Python: >=3.8
